lsga/__init__.py
lsga/engine.py
lsga/engine_wrapper.py
lsga/mpiutil.py
lsga/analysis/__init__.py
lsga/analysis/console_output.py
lsga/analysis/fitness_store.py
lsga/components/__init__.py
lsga/components/binary_individual.py
lsga/components/decimal_individual.py
lsga/components/individual.py
lsga/components/population.py
lsga/operators/__init__.py
lsga/operators/crossover/__init__.py
lsga/operators/crossover/uniform_crossover.py
lsga/operators/mutation/__init__.py
lsga/operators/mutation/flip_bit_big_mutation.py
lsga/operators/mutation/flip_bit_mutation.py
lsga/operators/selection/__init__.py
lsga/operators/selection/exponential_ranking_selection.py
lsga/operators/selection/linear_ranking_selection.py
lsga/operators/selection/roulette_wheel_selection.py
lsga/operators/selection/tournament_selection.py
lsga/plugin_interfaces/__init__.py
lsga/plugin_interfaces/analysis.py
lsga/plugin_interfaces/metaclasses.py
lsga/plugin_interfaces/operators/__init__.py
lsga/plugin_interfaces/operators/crossover.py
lsga/plugin_interfaces/operators/mutation.py
lsga/plugin_interfaces/operators/selection.py
lsga/tests/__init__.py
lsga/tests/dynamic_linear_scaling_test.py
lsga/tests/engine_test.py
lsga/tests/exponential_ranking_selection_test.py
lsga/tests/flip_bit_big_mutation_test.py
lsga/tests/flip_bit_mutation_test.py
lsga/tests/individual_test.py
lsga/tests/linear_ranking_selection_test.py
lsga/tests/linear_scaling_test.py
lsga/tests/mpiutil_test.py
lsga/tests/population_test.py
lsga/tests/roulette_wheel_selection_test.py
lsga/tests/test_all.py
lsga/tests/tournament_selection_test.py
lsga/tests/uniform_crossover_test.py
lsga-0.6.0.dist-info/METADATA
lsga-0.6.0.dist-info/RECORD
lsga-0.6.0.dist-info/WHEEL
lsga-0.6.0.dist-info/top_level.txt
